seinei/__init__.py
seinei/fetch.py
seinei/output.py
seinei/tilt.py
seinei/ui.py
seinei/bin/seinei.py
seinei/bin/seineiplot.py
seinei-0.0.1.dist-info/LICENSE
seinei-0.0.1.dist-info/METADATA
seinei-0.0.1.dist-info/WHEEL
seinei-0.0.1.dist-info/entry_points.txt
seinei-0.0.1.dist-info/top_level.txt
seinei-0.0.1.dist-info/RECORD
