Metadata-Version: 2.1
Name: seinei
Version: 0.0.1
Summary: Seismometerneigungssignalanalysator - Seismometer tilt signal analyzer
Author: Michael Christoffersen
Author-email: mchristo28@gmail.com
Project-URL: documentation, https://github.com/mchristoffersen/SeiNei/wiki
Project-URL: repository, https://github.com/mchristoffersen/SeiNei
Requires-Python: >=3.6
License-File: LICENSE
Requires-Dist: numpy
Requires-Dist: matplotlib
Requires-Dist: obspy
